gentoricass/__init__.py
gentoricass/main.py
gentoricass-2.0.dist-info/LICENSE.txt
gentoricass-2.0.dist-info/METADATA
gentoricass-2.0.dist-info/WHEEL
gentoricass-2.0.dist-info/top_level.txt
gentoricass-2.0.dist-info/RECORD
