Metadata-Version: 2.1
Name: gentoricass
Version: 2.0
Summary: A beginner-friendly programming language built on Python
Home-page: UNKNOWN
Author: Dickily
Author-email: dickilyyiu@gmail.com
License: MIT
Platform: UNKNOWN
Classifier: Programming Language :: Python :: 3
Classifier: License :: OSI Approved :: MIT License
Classifier: Operating System :: OS Independent
Requires-Python: >=3.8
Requires-Dist: Faker>=15.3.4
